<?xml version="1.0" encoding="UTF-8"?><database>
    <element db_object_id="86ba3ceb4723311061b6a09f016d43f9" label="Visitors" max_length="40" name="x_725196_visitor_0_visitors" type="collection">
        <element attributes="edge_encryption_enabled=true" label="Access Level" max_length="40" name="access_level" type="string"/>
        <element attributes="edge_encryption_enabled=true" label="Company" max_length="40" name="company" type="string"/>
        <element attributes="edge_encryption_enabled=true" label="Email" max_length="40" name="email" type="string"/>
        <element attributes="edge_encryption_enabled=true" label="First Name" max_length="40" name="first_name" type="string"/>
        <element attributes="edge_encryption_enabled=true" label="Last Name" max_length="40" name="last_name" type="string"/>
        <element attributes="edge_encryption_enabled=true" label="Location" max_length="40" name="location" type="string"/>
        <element attributes="edge_encryption_enabled=true" default="javascript:global.getNextObjNumberPadded" label="Number" max_length="40" name="number" type="string"/>
        <element attributes="edge_encryption_enabled=true" default="javascript:global.getNextObjNumberPadded" label="Number 2" max_length="40" name="number_2" type="string"/>
        <element attributes="edge_encryption_enabled=true" label="Phone Number" max_length="40" name="phone_number" type="string"/>
        <element label="RoleInCompany" max_length="40" name="roleincompany" type="string"/>
        <element attributes="edge_encryption_enabled=true" label="Title" max_length="40" name="title" type="string"/>
    </element>
</database>
